classroom_notice_board_rest_clinet-0.3.1.dist-info/METADATA
classroom_notice_board_rest_clinet-0.3.1.dist-info/WHEEL
classroom_notice_board_rest_clinet-0.3.1.dist-info/entry_points.txt
classroom_notice_board_rest_clinet/__init__.py
classroom_notice_board_rest_clinet/main.py
classroom_notice_board_rest_clinet/restclient.py
classroom_notice_board_rest_clinet/toolbox/__init__.py
classroom_notice_board_rest_clinet/toolbox/extractor.py
classroom_notice_board_rest_clinet/toolbox/makeup_artist.py
classroom_notice_board_rest_clinet-0.3.1.dist-info/RECORD
