Metadata-Version: 2.1
Name: classroom-notice-board-rest-clinet
Version: 0.3.1
Summary: https://github.com/edu-data-mario/classroom-notice-board rest clinet
Author-Email: dmario24 <data.mario24@gmail.com>
License: MIT
Project-URL: Homepage, https://github.com/edu-data-mario/classroom-notice-board-rest-clinet
Project-URL: Bug tracker, https://github.com/edu-data-mario/classroom-notice-board-rest-clinet/issues
Requires-Python: >=3.7
Requires-Dist: requests>=2.31.0
